<?xml version="1.0" encoding="utf-8"?>
<!--
  ALPHA Update Channel
  This file is checked by EveLens ALPHA builds for updates.
-->
<evelens>
  <releases>
    <release>
      <date>2026-03-19</date>
      <version>1.0.0.46</version>
      <url>https://github.com/aliacollins/evelens/releases/tag/alpha</url>
      <autopatchurl>https://github.com/aliacollins/evelens/releases/download/alpha/EveLens-install-1.0.0.exe</autopatchurl>
      <autopatchargs>/SILENT</autopatchargs>
      <message><![CDATA[EveLens 1.0.0-alpha.46

Fix promote.ps1 version counter for cross-channel promotions]]></message>
    </release>
    <release>
      <date>2026-03-19</date>
      <version>1.0.0.45</version>
      <url>https://github.com/aliacollins/evelens/releases/tag/alpha</url>
      <autopatchurl>https://github.com/aliacollins/evelens/releases/download/alpha/EveLens-install-1.0.0.exe</autopatchurl>
      <autopatchargs>/SILENT</autopatchargs>
      <message><![CDATA[EveLens 1.0.0-alpha.45

Fix version regression, add branching policy]]></message>
    </release>
    <release>
      <date>2026-03-19</date>
      <version>1.0.0.1</version>
      <url>https://github.com/aliacollins/evelens/releases/tag/alpha</url>
      <autopatchurl>https://github.com/aliacollins/evelens/releases/download/alpha/EveLens-install-1.0.0.exe</autopatchurl>
      <autopatchargs>/SILENT</autopatchargs>
      <message><![CDATA[EveLens 1.0.0-alpha.1

ESI health state machine, SDE Catalyst expansion, debug isolation, diagnostic viewer]]></message>
    </release>
    <release>
      <date>2026-03-16</date>
      <version>1.0.0.44</version>
      <url>https://github.com/aliacollins/evelens/releases/tag/alpha</url>
      <autopatchurl>https://github.com/aliacollins/evelens/releases/download/alpha/EveLens-install-1.0.0.exe</autopatchurl>
      <autopatchargs>/SILENT</autopatchargs>
      <message><![CDATA[EveLens 1.0.0-alpha.44

Fix promote.ps1 cross-branch merge strategy for alpha-to-beta promotions]]></message>
    </release>
    <release>
      <date>2026-03-16</date>
      <version>1.0.0.43</version>
      <url>https://github.com/aliacollins/evelens/releases/tag/alpha</url>
      <autopatchurl>https://github.com/aliacollins/evelens/releases/download/alpha/EveLens-install-1.0.0.exe</autopatchurl>
      <autopatchargs>/SILENT</autopatchargs>
      <message><![CDATA[EveLens 1.0.0-alpha.43

Fix window position save/restore across restarts and multi-monitor setups]]></message>
    </release>
    <release>
      <date>2026-03-16</date>
      <version>1.0.0.42</version>
      <url>https://github.com/aliacollins/evelens/releases/tag/alpha</url>
      <autopatchurl>https://github.com/aliacollins/evelens/releases/download/alpha/EveLens-install-1.0.0.exe</autopatchurl>
      <autopatchargs>/SILENT</autopatchargs>
      <message><![CDATA[EveLens 1.0.0-alpha.42

Beta launch prep: scrollbar fix, window position save, tray toggle, group collapse/reorder, README rewrite]]></message>
    </release>
    <release>
      <date>2026-03-16</date>
      <version>1.0.0.41</version>
      <url>https://github.com/aliacollins/evelens/releases/tag/alpha</url>
      <autopatchurl>https://github.com/aliacollins/evelens/releases/download/alpha/EveLens-install-1.0.0.exe</autopatchurl>
      <autopatchargs>/SILENT</autopatchargs>
      <message><![CDATA[EveLens 1.0.0-alpha.41

Smarter error notifications: ESI hiccups suppressed, persistent errors show the cause]]></message>
    </release>
    <release>
      <date>2026-03-16</date>
      <version>1.0.0.40</version>
      <url>https://github.com/aliacollins/evelens/releases/tag/alpha</url>
      <autopatchurl>https://github.com/aliacollins/evelens/releases/download/alpha/EveLens-install-1.0.0.exe</autopatchurl>
      <autopatchargs>/SILENT</autopatchargs>
      <message><![CDATA[EveLens 1.0.0-alpha.40

Fix auto-update: hard kill process so Inno installer can proceed]]></message>
    </release>
    <release>
      <date>2026-03-16</date>
      <version>1.0.0.39</version>
      <url>https://github.com/aliacollins/evelens/releases/tag/alpha</url>
      <autopatchurl>https://github.com/aliacollins/evelens/releases/download/alpha/EveLens-install-1.0.0.exe</autopatchurl>
      <autopatchargs>/SILENT</autopatchargs>
      <message><![CDATA[EveLens 1.0.0-alpha.39

Remove retry (caused ESI error cascade at scale), suppress PI idle spam from activity log]]></message>
    </release>
    <release>
      <date>2026-03-16</date>
      <version>1.0.0.38</version>
      <url>https://github.com/aliacollins/evelens/releases/tag/alpha</url>
      <autopatchurl>https://github.com/aliacollins/evelens/releases/download/alpha/EveLens-install-1.0.0.exe</autopatchurl>
      <autopatchargs>/SILENT</autopatchargs>
      <message><![CDATA[EveLens 1.0.0-alpha.38

Fix update dialog: prevent duplicate windows, scrollable release notes with proper buttons]]></message>
    </release>
  </releases>
  <datafiles>
  </datafiles>
</evelens>